notion2velog/__init__.py
notion2velog/main.py
notion2velog/notion_api.py
notion2velog/settings.py
notion2velog/utils.py
notion2velog/web_actions.py
notion2velog-0.1.dist-info/METADATA
notion2velog-0.1.dist-info/WHEEL
notion2velog-0.1.dist-info/entry_points.txt
notion2velog-0.1.dist-info/top_level.txt
notion2velog-0.1.dist-info/RECORD
